{
  "flights" : [ {
    "flightId" : 321,
    "airline" : {
      "airlineId" : 17,
      "name" : "Iberia"
    },
    "sourceAirport" : {
      "airportId" : 17,
      "name" : "Adolfo Suárez Madrid–Barajas Airport",
      "city" : {
        "cityId" : 17,
        "name" : "Madrid",
        "country" : {
          "countryId" : 17,
          "name" : "Spain"
        }
      },
      "latitude" : 40.471,
      "longitude" : -3.5626
    },
    "destinationAirport" : {
      "airportId" : 18,
      "name" : "Istanbul Atatürk Airport",
      "city" : {
        "cityId" : 18,
        "name" : "Istanbul",
        "country" : {
          "countryId" : 18,
          "name" : "Turkey"
        }
      },
      "latitude" : 40.9767,
      "longitude" : 28.815
    },
    "price" : 271.33
  }, {
    "flightId" : 335,
    "airline" : {
      "airlineId" : 18,
      "name" : "Turkish Airlines"
    },
    "sourceAirport" : {
      "airportId" : 18,
      "name" : "Istanbul Atatürk Airport",
      "city" : {
        "cityId" : 18,
        "name" : "Istanbul",
        "country" : {
          "countryId" : 18,
          "name" : "Turkey"
        }
      },
      "latitude" : 40.9767,
      "longitude" : 28.815
    },
    "destinationAirport" : {
      "airportId" : 12,
      "name" : "Chhatrapati Shivaji Maharaj International Airport",
      "city" : {
        "cityId" : 12,
        "name" : "Mumbai",
        "country" : {
          "countryId" : 12,
          "name" : "India"
        }
      },
      "latitude" : 19.0887,
      "longitude" : 72.8679
    },
    "price" : 481.99
  }, {
    "flightId" : 218,
    "airline" : {
      "airlineId" : 12,
      "name" : "Air India"
    },
    "sourceAirport" : {
      "airportId" : 12,
      "name" : "Chhatrapati Shivaji Maharaj International Airport",
      "city" : {
        "cityId" : 12,
        "name" : "Mumbai",
        "country" : {
          "countryId" : 12,
          "name" : "India"
        }
      },
      "latitude" : 19.0887,
      "longitude" : 72.8679
    },
    "destinationAirport" : {
      "airportId" : 9,
      "name" : "Beijing Capital International Airport",
      "city" : {
        "cityId" : 9,
        "name" : "Beijing",
        "country" : {
          "countryId" : 9,
          "name" : "China"
        }
      },
      "latitude" : 40.0799,
      "longitude" : 116.6031
    },
    "price" : 476.59
  }, {
    "flightId" : 170,
    "airline" : {
      "airlineId" : 9,
      "name" : "Air China"
    },
    "sourceAirport" : {
      "airportId" : 9,
      "name" : "Beijing Capital International Airport",
      "city" : {
        "cityId" : 9,
        "name" : "Beijing",
        "country" : {
          "countryId" : 9,
          "name" : "China"
        }
      },
      "latitude" : 40.0799,
      "longitude" : 116.6031
    },
    "destinationAirport" : {
      "airportId" : 19,
      "name" : "Tokyo Haneda Airport",
      "city" : {
        "cityId" : 19,
        "name" : "Tokyo",
        "country" : {
          "countryId" : 19,
          "name" : "Japan"
        }
      },
      "latitude" : 35.5494,
      "longitude" : 139.7798
    },
    "price" : 209.08
  } ]
}